{
  "object": "tcgjson_product_detail_cache_entry",
  "version": 1,
  "generatedAt": "2026-06-29T23:20:45Z",
  "tcgplayerProductId": 455218,
  "details": {
    "customListings": 0.0,
    "shippingCategoryId": 1.0,
    "duplicate": true,
    "productLineUrlName": "Magic",
    "productTypeName": "Cards",
    "productUrlName": "Quakefoot Cyclops",
    "productTypeId": 1.0,
    "rarityName": "Common",
    "sealed": false,
    "marketPrice": 0.14,
    "customAttributes": {
      "formats": null,
      "description": "When Quakefoot Cyclops enters the battlefield, up to two target creatures can't block this turn.\r\n<br>\r\nCycling 1R <em>(1R, Discard this card: Draw a card.)</em>\r\n<br>\r\nWhen you cycle Quakefoot Cyclops, target creature can't block this turn.",
      "powerNumber": "4",
      "detailNote": "This product is a Presale item with an estimated shipping date of 12/2/2022. Please keep in mind card details, including rarity and card name, may change up until release date as information is updated.",
      "color": [
        "Red"
      ],
      "fullType": "Creature — Cyclops",
      "releaseDate": "2022-12-02T00:00:00Z",
      "number": "583",
      "cardType": [
        "Creature"
      ],
      "convertedCost": "5",
      "rarityDbName": "C",
      "power": "4",
      "flavorText": "",
      "toughnessNumber": "4",
      "toughness": "4"
    },
    "lowestPriceWithShipping": 0.03,
    "productName": "Quakefoot Cyclops",
    "setId": 3185.0,
    "setCode": "J22",
    "productId": 455218.0,
    "imageCount": 1.0,
    "score": 1.2552725,
    "setName": "Jumpstart 2022",
    "sellers": 186.0,
    "foilOnly": false,
    "setUrlName": "Jumpstart 2022",
    "sellerListable": true,
    "productLineId": 1.0,
    "productStatusId": 1.0,
    "productLineName": "Magic: The Gathering",
    "maxFulfillableQuantity": 255.0,
    "normalOnly": true,
    "listings": 197.0,
    "lowestPrice": 0.01,
    "medianPrice": 0.235,
    "formattedAttributes": {
      "Rarity": "C",
      "#": "583",
      "Card Type": "Creature — Cyclops",
      "P / T": "4 / 4",
      "Description": "When Quakefoot Cyclops enters the battlefield, up to two target creatures can't block this turn.\r\n<br>\r\nCycling 1R <em>(1R, Discard this card: Draw a card.)</em>\r\n<br>\r\nWhen you cycle Quakefoot Cyclops, target creature can't block this turn.",
      "Artist": "Mike Bierek"
    },
    "skus": [
      {
        "sku": 6750615,
        "condition": "Near Mint",
        "variant": "Normal",
        "language": "Chinese (S)"
      },
      {
        "sku": 6750616,
        "condition": "Lightly Played",
        "variant": "Normal",
        "language": "Chinese (S)"
      },
      {
        "sku": 6750617,
        "condition": "Moderately Played",
        "variant": "Normal",
        "language": "Chinese (S)"
      },
      {
        "sku": 6750618,
        "condition": "Heavily Played",
        "variant": "Normal",
        "language": "Chinese (S)"
      },
      {
        "sku": 6750619,
        "condition": "Damaged",
        "variant": "Normal",
        "language": "Chinese (S)"
      },
      {
        "sku": 6750610,
        "condition": "Near Mint",
        "variant": "Normal",
        "language": "English"
      },
      {
        "sku": 6750611,
        "condition": "Lightly Played",
        "variant": "Normal",
        "language": "English"
      },
      {
        "sku": 6750612,
        "condition": "Moderately Played",
        "variant": "Normal",
        "language": "English"
      },
      {
        "sku": 6750613,
        "condition": "Heavily Played",
        "variant": "Normal",
        "language": "English"
      },
      {
        "sku": 6750614,
        "condition": "Damaged",
        "variant": "Normal",
        "language": "English"
      },
      {
        "sku": 6750620,
        "condition": "Near Mint",
        "variant": "Normal",
        "language": "French"
      },
      {
        "sku": 6750621,
        "condition": "Lightly Played",
        "variant": "Normal",
        "language": "French"
      },
      {
        "sku": 6750622,
        "condition": "Moderately Played",
        "variant": "Normal",
        "language": "French"
      },
      {
        "sku": 6750623,
        "condition": "Heavily Played",
        "variant": "Normal",
        "language": "French"
      },
      {
        "sku": 6750624,
        "condition": "Damaged",
        "variant": "Normal",
        "language": "French"
      },
      {
        "sku": 6750625,
        "condition": "Near Mint",
        "variant": "Normal",
        "language": "German"
      },
      {
        "sku": 6750626,
        "condition": "Lightly Played",
        "variant": "Normal",
        "language": "German"
      },
      {
        "sku": 6750627,
        "condition": "Moderately Played",
        "variant": "Normal",
        "language": "German"
      },
      {
        "sku": 6750628,
        "condition": "Heavily Played",
        "variant": "Normal",
        "language": "German"
      },
      {
        "sku": 6750629,
        "condition": "Damaged",
        "variant": "Normal",
        "language": "German"
      },
      {
        "sku": 6750630,
        "condition": "Near Mint",
        "variant": "Normal",
        "language": "Italian"
      },
      {
        "sku": 6750631,
        "condition": "Lightly Played",
        "variant": "Normal",
        "language": "Italian"
      },
      {
        "sku": 6750632,
        "condition": "Moderately Played",
        "variant": "Normal",
        "language": "Italian"
      },
      {
        "sku": 6750633,
        "condition": "Heavily Played",
        "variant": "Normal",
        "language": "Italian"
      },
      {
        "sku": 6750634,
        "condition": "Damaged",
        "variant": "Normal",
        "language": "Italian"
      },
      {
        "sku": 6750635,
        "condition": "Near Mint",
        "variant": "Normal",
        "language": "Japanese"
      },
      {
        "sku": 6750636,
        "condition": "Lightly Played",
        "variant": "Normal",
        "language": "Japanese"
      },
      {
        "sku": 6750637,
        "condition": "Moderately Played",
        "variant": "Normal",
        "language": "Japanese"
      },
      {
        "sku": 6750638,
        "condition": "Heavily Played",
        "variant": "Normal",
        "language": "Japanese"
      },
      {
        "sku": 6750639,
        "condition": "Damaged",
        "variant": "Normal",
        "language": "Japanese"
      },
      {
        "sku": 6750640,
        "condition": "Near Mint",
        "variant": "Normal",
        "language": "Spanish"
      },
      {
        "sku": 6750641,
        "condition": "Lightly Played",
        "variant": "Normal",
        "language": "Spanish"
      },
      {
        "sku": 6750642,
        "condition": "Moderately Played",
        "variant": "Normal",
        "language": "Spanish"
      },
      {
        "sku": 6750643,
        "condition": "Heavily Played",
        "variant": "Normal",
        "language": "Spanish"
      },
      {
        "sku": 6750644,
        "condition": "Damaged",
        "variant": "Normal",
        "language": "Spanish"
      }
    ]
  }
}
