{
  "object": "tcgjson_product_detail_cache_entry",
  "version": 1,
  "generatedAt": "2026-06-29T22:38:20Z",
  "tcgplayerProductId": 199470,
  "details": {
    "customListings": 0.0,
    "shippingCategoryId": 1.0,
    "duplicate": false,
    "productLineUrlName": "Magic",
    "productTypeName": "Cards",
    "productUrlName": "Food Token 016",
    "productTypeId": 1.0,
    "rarityName": "Token",
    "sealed": false,
    "marketPrice": 0.17,
    "customAttributes": {
      "formats": null,
      "description": "2, T, Sacrifice this artifact: You gain 3 life.",
      "powerNumber": null,
      "color": [
        "Colorless"
      ],
      "fullType": "Token Artifact — Food",
      "releaseDate": "2019-10-04T00:00:00Z",
      "number": "16",
      "cardType": [
        "Artifact"
      ],
      "rarityDbName": "T",
      "power": null,
      "flavorText": "",
      "toughnessNumber": null,
      "toughness": null
    },
    "lowestPriceWithShipping": 0.04,
    "productName": "Food Token (016)",
    "setId": 2494.0,
    "setCode": "ELD",
    "productId": 199470.0,
    "imageCount": 1.0,
    "score": 2.3838153,
    "setName": "Throne of Eldraine",
    "sellers": 256.0,
    "foilOnly": false,
    "setUrlName": "Throne of Eldraine",
    "sellerListable": true,
    "productLineId": 1.0,
    "productStatusId": 1.0,
    "productLineName": "Magic: The Gathering",
    "maxFulfillableQuantity": 255.0,
    "normalOnly": true,
    "listings": 277.0,
    "lowestPrice": 0.04,
    "medianPrice": 0.22,
    "formattedAttributes": {
      "Rarity": "T",
      "#": "16",
      "Card Type": "Token Artifact — Food",
      "Description": "2, T, Sacrifice this artifact: You gain 3 life.",
      "Artist": "Randy Gallegos"
    },
    "skus": [
      {
        "sku": 4209658,
        "condition": "Near Mint",
        "variant": "Normal",
        "language": "Chinese (S)"
      },
      {
        "sku": 4209659,
        "condition": "Lightly Played",
        "variant": "Normal",
        "language": "Chinese (S)"
      },
      {
        "sku": 4209660,
        "condition": "Moderately Played",
        "variant": "Normal",
        "language": "Chinese (S)"
      },
      {
        "sku": 4209661,
        "condition": "Heavily Played",
        "variant": "Normal",
        "language": "Chinese (S)"
      },
      {
        "sku": 4209662,
        "condition": "Damaged",
        "variant": "Normal",
        "language": "Chinese (S)"
      },
      {
        "sku": 4209663,
        "condition": "Near Mint",
        "variant": "Normal",
        "language": "Chinese (T)"
      },
      {
        "sku": 4209664,
        "condition": "Lightly Played",
        "variant": "Normal",
        "language": "Chinese (T)"
      },
      {
        "sku": 4209665,
        "condition": "Moderately Played",
        "variant": "Normal",
        "language": "Chinese (T)"
      },
      {
        "sku": 4209666,
        "condition": "Heavily Played",
        "variant": "Normal",
        "language": "Chinese (T)"
      },
      {
        "sku": 4209667,
        "condition": "Damaged",
        "variant": "Normal",
        "language": "Chinese (T)"
      },
      {
        "sku": 4209648,
        "condition": "Near Mint",
        "variant": "Normal",
        "language": "English"
      },
      {
        "sku": 4209649,
        "condition": "Lightly Played",
        "variant": "Normal",
        "language": "English"
      },
      {
        "sku": 4209650,
        "condition": "Moderately Played",
        "variant": "Normal",
        "language": "English"
      },
      {
        "sku": 4209651,
        "condition": "Heavily Played",
        "variant": "Normal",
        "language": "English"
      },
      {
        "sku": 4209652,
        "condition": "Damaged",
        "variant": "Normal",
        "language": "English"
      },
      {
        "sku": 4209668,
        "condition": "Near Mint",
        "variant": "Normal",
        "language": "French"
      },
      {
        "sku": 4209669,
        "condition": "Lightly Played",
        "variant": "Normal",
        "language": "French"
      },
      {
        "sku": 4209670,
        "condition": "Moderately Played",
        "variant": "Normal",
        "language": "French"
      },
      {
        "sku": 4209671,
        "condition": "Heavily Played",
        "variant": "Normal",
        "language": "French"
      },
      {
        "sku": 4209672,
        "condition": "Damaged",
        "variant": "Normal",
        "language": "French"
      },
      {
        "sku": 4209673,
        "condition": "Near Mint",
        "variant": "Normal",
        "language": "German"
      },
      {
        "sku": 4209674,
        "condition": "Lightly Played",
        "variant": "Normal",
        "language": "German"
      },
      {
        "sku": 4209675,
        "condition": "Moderately Played",
        "variant": "Normal",
        "language": "German"
      },
      {
        "sku": 4209676,
        "condition": "Heavily Played",
        "variant": "Normal",
        "language": "German"
      },
      {
        "sku": 4209677,
        "condition": "Damaged",
        "variant": "Normal",
        "language": "German"
      },
      {
        "sku": 4209678,
        "condition": "Near Mint",
        "variant": "Normal",
        "language": "Italian"
      },
      {
        "sku": 4209679,
        "condition": "Lightly Played",
        "variant": "Normal",
        "language": "Italian"
      },
      {
        "sku": 4209680,
        "condition": "Moderately Played",
        "variant": "Normal",
        "language": "Italian"
      },
      {
        "sku": 4209681,
        "condition": "Heavily Played",
        "variant": "Normal",
        "language": "Italian"
      },
      {
        "sku": 4209682,
        "condition": "Damaged",
        "variant": "Normal",
        "language": "Italian"
      },
      {
        "sku": 4209683,
        "condition": "Near Mint",
        "variant": "Normal",
        "language": "Japanese"
      },
      {
        "sku": 4209684,
        "condition": "Lightly Played",
        "variant": "Normal",
        "language": "Japanese"
      },
      {
        "sku": 4209685,
        "condition": "Moderately Played",
        "variant": "Normal",
        "language": "Japanese"
      },
      {
        "sku": 4209686,
        "condition": "Heavily Played",
        "variant": "Normal",
        "language": "Japanese"
      },
      {
        "sku": 4209687,
        "condition": "Damaged",
        "variant": "Normal",
        "language": "Japanese"
      },
      {
        "sku": 4209693,
        "condition": "Near Mint",
        "variant": "Normal",
        "language": "Korean"
      },
      {
        "sku": 4209694,
        "condition": "Lightly Played",
        "variant": "Normal",
        "language": "Korean"
      },
      {
        "sku": 4209695,
        "condition": "Moderately Played",
        "variant": "Normal",
        "language": "Korean"
      },
      {
        "sku": 4209696,
        "condition": "Heavily Played",
        "variant": "Normal",
        "language": "Korean"
      },
      {
        "sku": 4209697,
        "condition": "Damaged",
        "variant": "Normal",
        "language": "Korean"
      },
      {
        "sku": 4209698,
        "condition": "Near Mint",
        "variant": "Normal",
        "language": "Portuguese"
      },
      {
        "sku": 4209699,
        "condition": "Lightly Played",
        "variant": "Normal",
        "language": "Portuguese"
      },
      {
        "sku": 4209700,
        "condition": "Moderately Played",
        "variant": "Normal",
        "language": "Portuguese"
      },
      {
        "sku": 4209701,
        "condition": "Heavily Played",
        "variant": "Normal",
        "language": "Portuguese"
      },
      {
        "sku": 4209702,
        "condition": "Damaged",
        "variant": "Normal",
        "language": "Portuguese"
      },
      {
        "sku": 4209703,
        "condition": "Near Mint",
        "variant": "Normal",
        "language": "Russian"
      },
      {
        "sku": 4209704,
        "condition": "Lightly Played",
        "variant": "Normal",
        "language": "Russian"
      },
      {
        "sku": 4209705,
        "condition": "Moderately Played",
        "variant": "Normal",
        "language": "Russian"
      },
      {
        "sku": 4209706,
        "condition": "Heavily Played",
        "variant": "Normal",
        "language": "Russian"
      },
      {
        "sku": 4209707,
        "condition": "Damaged",
        "variant": "Normal",
        "language": "Russian"
      },
      {
        "sku": 4209708,
        "condition": "Near Mint",
        "variant": "Normal",
        "language": "Spanish"
      },
      {
        "sku": 4209709,
        "condition": "Lightly Played",
        "variant": "Normal",
        "language": "Spanish"
      },
      {
        "sku": 4209710,
        "condition": "Moderately Played",
        "variant": "Normal",
        "language": "Spanish"
      },
      {
        "sku": 4209711,
        "condition": "Heavily Played",
        "variant": "Normal",
        "language": "Spanish"
      },
      {
        "sku": 4209712,
        "condition": "Damaged",
        "variant": "Normal",
        "language": "Spanish"
      }
    ]
  }
}
