{
  "object": "tcgjson_product_detail_cache_entry",
  "version": 1,
  "generatedAt": "2026-06-29T23:12:26Z",
  "tcgplayerProductId": 272927,
  "details": {
    "customListings": 0.0,
    "shippingCategoryId": 1.0,
    "duplicate": false,
    "productLineUrlName": "Magic",
    "productTypeName": "Cards",
    "productUrlName": "Gut True Soul Zealot",
    "productTypeId": 1.0,
    "rarityName": "Uncommon",
    "sealed": false,
    "marketPrice": 0.18,
    "customAttributes": {
      "formats": null,
      "description": "Whenever you attack, you may sacrifice another creature or an artifact. If you do, create a 4/1 black Skeleton creature token with menace that's tapped and attacking. <em>(It can't be blocked except by two or more creatures.)</em>\r\n<br>\r\nChoose a Background <em>(You can have a Background as a second commander.)</em>",
      "powerNumber": "2",
      "color": [
        "Red"
      ],
      "fullType": "Legendary Creature — Goblin Shaman",
      "releaseDate": "2022-06-10T00:00:00Z",
      "number": "180",
      "cardType": [
        "Legendary",
        "Creature"
      ],
      "convertedCost": "3",
      "rarityDbName": "U",
      "power": "2",
      "flavorText": "",
      "toughnessNumber": "2",
      "toughness": "2"
    },
    "lowestPriceWithShipping": 0.01,
    "productName": "Gut, True Soul Zealot",
    "setId": 3047.0,
    "setCode": "CLB",
    "productId": 272927.0,
    "imageCount": 1.0,
    "score": 2.6757784,
    "setName": "Commander Legends: Battle for Baldur's Gate",
    "sellers": 713.0,
    "foilOnly": false,
    "setUrlName": "Commander Legends Battle for Baldurs Gate",
    "sellerListable": true,
    "productLineId": 1.0,
    "productStatusId": 1.0,
    "productLineName": "Magic: The Gathering",
    "maxFulfillableQuantity": 255.0,
    "normalOnly": false,
    "listings": 881.0,
    "lowestPrice": 0.01,
    "medianPrice": 0.25,
    "formattedAttributes": {
      "Rarity": "U",
      "#": "180",
      "Card Type": "Legendary Creature — Goblin Shaman",
      "P / T": "2 / 2",
      "Description": "Whenever you attack, you may sacrifice another creature or an artifact. If you do, create a 4/1 black Skeleton creature token with menace that's tapped and attacking. <em>(It can't be blocked except by two or more creatures.)</em>\r\n<br>\r\nChoose a Background <em>(You can have a Background as a second commander.)</em>",
      "Artist": "Wayne Reynolds"
    },
    "skus": [
      {
        "sku": 5619411,
        "condition": "Near Mint",
        "variant": "Normal",
        "language": "Chinese (S)"
      },
      {
        "sku": 5619412,
        "condition": "Lightly Played",
        "variant": "Normal",
        "language": "Chinese (S)"
      },
      {
        "sku": 5619413,
        "condition": "Moderately Played",
        "variant": "Normal",
        "language": "Chinese (S)"
      },
      {
        "sku": 5619414,
        "condition": "Heavily Played",
        "variant": "Normal",
        "language": "Chinese (S)"
      },
      {
        "sku": 5619415,
        "condition": "Damaged",
        "variant": "Normal",
        "language": "Chinese (S)"
      },
      {
        "sku": 5619416,
        "condition": "Near Mint",
        "variant": "Foil",
        "language": "Chinese (S)"
      },
      {
        "sku": 5619417,
        "condition": "Lightly Played",
        "variant": "Foil",
        "language": "Chinese (S)"
      },
      {
        "sku": 5619418,
        "condition": "Moderately Played",
        "variant": "Foil",
        "language": "Chinese (S)"
      },
      {
        "sku": 5619419,
        "condition": "Heavily Played",
        "variant": "Foil",
        "language": "Chinese (S)"
      },
      {
        "sku": 5619420,
        "condition": "Damaged",
        "variant": "Foil",
        "language": "Chinese (S)"
      },
      {
        "sku": 5619421,
        "condition": "Near Mint",
        "variant": "Normal",
        "language": "Chinese (T)"
      },
      {
        "sku": 5619422,
        "condition": "Lightly Played",
        "variant": "Normal",
        "language": "Chinese (T)"
      },
      {
        "sku": 5619423,
        "condition": "Moderately Played",
        "variant": "Normal",
        "language": "Chinese (T)"
      },
      {
        "sku": 5619424,
        "condition": "Heavily Played",
        "variant": "Normal",
        "language": "Chinese (T)"
      },
      {
        "sku": 5619425,
        "condition": "Damaged",
        "variant": "Normal",
        "language": "Chinese (T)"
      },
      {
        "sku": 5619426,
        "condition": "Near Mint",
        "variant": "Foil",
        "language": "Chinese (T)"
      },
      {
        "sku": 5619427,
        "condition": "Lightly Played",
        "variant": "Foil",
        "language": "Chinese (T)"
      },
      {
        "sku": 5619428,
        "condition": "Moderately Played",
        "variant": "Foil",
        "language": "Chinese (T)"
      },
      {
        "sku": 5619429,
        "condition": "Heavily Played",
        "variant": "Foil",
        "language": "Chinese (T)"
      },
      {
        "sku": 5619430,
        "condition": "Damaged",
        "variant": "Foil",
        "language": "Chinese (T)"
      },
      {
        "sku": 5619401,
        "condition": "Near Mint",
        "variant": "Normal",
        "language": "English"
      },
      {
        "sku": 5619402,
        "condition": "Lightly Played",
        "variant": "Normal",
        "language": "English"
      },
      {
        "sku": 5619403,
        "condition": "Moderately Played",
        "variant": "Normal",
        "language": "English"
      },
      {
        "sku": 5619404,
        "condition": "Heavily Played",
        "variant": "Normal",
        "language": "English"
      },
      {
        "sku": 5619405,
        "condition": "Damaged",
        "variant": "Normal",
        "language": "English"
      },
      {
        "sku": 5619406,
        "condition": "Near Mint",
        "variant": "Foil",
        "language": "English"
      },
      {
        "sku": 5619407,
        "condition": "Lightly Played",
        "variant": "Foil",
        "language": "English"
      },
      {
        "sku": 5619408,
        "condition": "Moderately Played",
        "variant": "Foil",
        "language": "English"
      },
      {
        "sku": 5619409,
        "condition": "Heavily Played",
        "variant": "Foil",
        "language": "English"
      },
      {
        "sku": 5619410,
        "condition": "Damaged",
        "variant": "Foil",
        "language": "English"
      },
      {
        "sku": 5619431,
        "condition": "Near Mint",
        "variant": "Normal",
        "language": "French"
      },
      {
        "sku": 5619432,
        "condition": "Lightly Played",
        "variant": "Normal",
        "language": "French"
      },
      {
        "sku": 5619433,
        "condition": "Moderately Played",
        "variant": "Normal",
        "language": "French"
      },
      {
        "sku": 5619434,
        "condition": "Heavily Played",
        "variant": "Normal",
        "language": "French"
      },
      {
        "sku": 5619435,
        "condition": "Damaged",
        "variant": "Normal",
        "language": "French"
      },
      {
        "sku": 5619436,
        "condition": "Near Mint",
        "variant": "Foil",
        "language": "French"
      },
      {
        "sku": 5619437,
        "condition": "Lightly Played",
        "variant": "Foil",
        "language": "French"
      },
      {
        "sku": 5619438,
        "condition": "Moderately Played",
        "variant": "Foil",
        "language": "French"
      },
      {
        "sku": 5619439,
        "condition": "Heavily Played",
        "variant": "Foil",
        "language": "French"
      },
      {
        "sku": 5619440,
        "condition": "Damaged",
        "variant": "Foil",
        "language": "French"
      },
      {
        "sku": 5619441,
        "condition": "Near Mint",
        "variant": "Normal",
        "language": "German"
      },
      {
        "sku": 5619442,
        "condition": "Lightly Played",
        "variant": "Normal",
        "language": "German"
      },
      {
        "sku": 5619443,
        "condition": "Moderately Played",
        "variant": "Normal",
        "language": "German"
      },
      {
        "sku": 5619444,
        "condition": "Heavily Played",
        "variant": "Normal",
        "language": "German"
      },
      {
        "sku": 5619445,
        "condition": "Damaged",
        "variant": "Normal",
        "language": "German"
      },
      {
        "sku": 5619446,
        "condition": "Near Mint",
        "variant": "Foil",
        "language": "German"
      },
      {
        "sku": 5619447,
        "condition": "Lightly Played",
        "variant": "Foil",
        "language": "German"
      },
      {
        "sku": 5619448,
        "condition": "Moderately Played",
        "variant": "Foil",
        "language": "German"
      },
      {
        "sku": 5619449,
        "condition": "Heavily Played",
        "variant": "Foil",
        "language": "German"
      },
      {
        "sku": 5619450,
        "condition": "Damaged",
        "variant": "Foil",
        "language": "German"
      },
      {
        "sku": 5619451,
        "condition": "Near Mint",
        "variant": "Normal",
        "language": "Italian"
      },
      {
        "sku": 5619452,
        "condition": "Lightly Played",
        "variant": "Normal",
        "language": "Italian"
      },
      {
        "sku": 5619453,
        "condition": "Moderately Played",
        "variant": "Normal",
        "language": "Italian"
      },
      {
        "sku": 5619454,
        "condition": "Heavily Played",
        "variant": "Normal",
        "language": "Italian"
      },
      {
        "sku": 5619455,
        "condition": "Damaged",
        "variant": "Normal",
        "language": "Italian"
      },
      {
        "sku": 5619456,
        "condition": "Near Mint",
        "variant": "Foil",
        "language": "Italian"
      },
      {
        "sku": 5619457,
        "condition": "Lightly Played",
        "variant": "Foil",
        "language": "Italian"
      },
      {
        "sku": 5619458,
        "condition": "Moderately Played",
        "variant": "Foil",
        "language": "Italian"
      },
      {
        "sku": 5619459,
        "condition": "Heavily Played",
        "variant": "Foil",
        "language": "Italian"
      },
      {
        "sku": 5619460,
        "condition": "Damaged",
        "variant": "Foil",
        "language": "Italian"
      },
      {
        "sku": 5619461,
        "condition": "Near Mint",
        "variant": "Normal",
        "language": "Japanese"
      },
      {
        "sku": 5619462,
        "condition": "Lightly Played",
        "variant": "Normal",
        "language": "Japanese"
      },
      {
        "sku": 5619463,
        "condition": "Moderately Played",
        "variant": "Normal",
        "language": "Japanese"
      },
      {
        "sku": 5619464,
        "condition": "Heavily Played",
        "variant": "Normal",
        "language": "Japanese"
      },
      {
        "sku": 5619465,
        "condition": "Damaged",
        "variant": "Normal",
        "language": "Japanese"
      },
      {
        "sku": 5619466,
        "condition": "Near Mint",
        "variant": "Foil",
        "language": "Japanese"
      },
      {
        "sku": 5619467,
        "condition": "Lightly Played",
        "variant": "Foil",
        "language": "Japanese"
      },
      {
        "sku": 5619468,
        "condition": "Moderately Played",
        "variant": "Foil",
        "language": "Japanese"
      },
      {
        "sku": 5619469,
        "condition": "Heavily Played",
        "variant": "Foil",
        "language": "Japanese"
      },
      {
        "sku": 5619470,
        "condition": "Damaged",
        "variant": "Foil",
        "language": "Japanese"
      },
      {
        "sku": 5619471,
        "condition": "Near Mint",
        "variant": "Normal",
        "language": "Korean"
      },
      {
        "sku": 5619472,
        "condition": "Lightly Played",
        "variant": "Normal",
        "language": "Korean"
      },
      {
        "sku": 5619473,
        "condition": "Moderately Played",
        "variant": "Normal",
        "language": "Korean"
      },
      {
        "sku": 5619474,
        "condition": "Heavily Played",
        "variant": "Normal",
        "language": "Korean"
      },
      {
        "sku": 5619475,
        "condition": "Damaged",
        "variant": "Normal",
        "language": "Korean"
      },
      {
        "sku": 5619476,
        "condition": "Near Mint",
        "variant": "Foil",
        "language": "Korean"
      },
      {
        "sku": 5619477,
        "condition": "Lightly Played",
        "variant": "Foil",
        "language": "Korean"
      },
      {
        "sku": 5619478,
        "condition": "Moderately Played",
        "variant": "Foil",
        "language": "Korean"
      },
      {
        "sku": 5619479,
        "condition": "Heavily Played",
        "variant": "Foil",
        "language": "Korean"
      },
      {
        "sku": 5619480,
        "condition": "Damaged",
        "variant": "Foil",
        "language": "Korean"
      },
      {
        "sku": 5619481,
        "condition": "Near Mint",
        "variant": "Normal",
        "language": "Portuguese"
      },
      {
        "sku": 5619482,
        "condition": "Lightly Played",
        "variant": "Normal",
        "language": "Portuguese"
      },
      {
        "sku": 5619483,
        "condition": "Moderately Played",
        "variant": "Normal",
        "language": "Portuguese"
      },
      {
        "sku": 5619484,
        "condition": "Heavily Played",
        "variant": "Normal",
        "language": "Portuguese"
      },
      {
        "sku": 5619485,
        "condition": "Damaged",
        "variant": "Normal",
        "language": "Portuguese"
      },
      {
        "sku": 5619486,
        "condition": "Near Mint",
        "variant": "Foil",
        "language": "Portuguese"
      },
      {
        "sku": 5619487,
        "condition": "Lightly Played",
        "variant": "Foil",
        "language": "Portuguese"
      },
      {
        "sku": 5619488,
        "condition": "Moderately Played",
        "variant": "Foil",
        "language": "Portuguese"
      },
      {
        "sku": 5619489,
        "condition": "Heavily Played",
        "variant": "Foil",
        "language": "Portuguese"
      },
      {
        "sku": 5619490,
        "condition": "Damaged",
        "variant": "Foil",
        "language": "Portuguese"
      },
      {
        "sku": 5619491,
        "condition": "Near Mint",
        "variant": "Normal",
        "language": "Spanish"
      },
      {
        "sku": 5619492,
        "condition": "Lightly Played",
        "variant": "Normal",
        "language": "Spanish"
      },
      {
        "sku": 5619493,
        "condition": "Moderately Played",
        "variant": "Normal",
        "language": "Spanish"
      },
      {
        "sku": 5619494,
        "condition": "Heavily Played",
        "variant": "Normal",
        "language": "Spanish"
      },
      {
        "sku": 5619495,
        "condition": "Damaged",
        "variant": "Normal",
        "language": "Spanish"
      },
      {
        "sku": 5619496,
        "condition": "Near Mint",
        "variant": "Foil",
        "language": "Spanish"
      },
      {
        "sku": 5619497,
        "condition": "Lightly Played",
        "variant": "Foil",
        "language": "Spanish"
      },
      {
        "sku": 5619498,
        "condition": "Moderately Played",
        "variant": "Foil",
        "language": "Spanish"
      },
      {
        "sku": 5619499,
        "condition": "Heavily Played",
        "variant": "Foil",
        "language": "Spanish"
      },
      {
        "sku": 5619500,
        "condition": "Damaged",
        "variant": "Foil",
        "language": "Spanish"
      }
    ]
  }
}
