{
  "object": "tcgjson_product_detail_cache_entry",
  "version": 1,
  "generatedAt": "2026-06-29T23:59:17Z",
  "tcgplayerProductId": 615034,
  "details": {
    "customListings": 0.0,
    "shippingCategoryId": 1.0,
    "duplicate": false,
    "productLineUrlName": "Magic",
    "productTypeName": "Cards",
    "productUrlName": "Interface Ace",
    "productTypeId": 1.0,
    "rarityName": "Common",
    "sealed": false,
    "marketPrice": 0.23,
    "customAttributes": {
      "formats": null,
      "description": "This creature saddles Mounts and crews Vehicles using its toughness rather than its power.\r\n<br>\r\nWhenever this creature becomes tapped during your turn, untap it. This ability triggers only once each turn.",
      "powerNumber": "0",
      "detailNote": "This product is a Presale item with an estimated shipping date of 2/14/2025. Please keep in mind card details, including rarity and card name, may change up until release date as information is updated.",
      "color": [
        "White"
      ],
      "fullType": "Artifact Creature — Robot Pilot",
      "releaseDate": "2025-02-14T00:00:00Z",
      "number": "17",
      "cardType": [
        "Artifact",
        "Creature"
      ],
      "convertedCost": "2",
      "rarityDbName": "C",
      "power": "0",
      "flavorText": "<em>To the Guidelight Voyagers, a vehicle is just another hardware upgrade.</em>",
      "toughnessNumber": "4",
      "toughness": "4"
    },
    "lowestPriceWithShipping": 0.01,
    "productName": "Interface Ace",
    "setId": 23874.0,
    "setCode": "DFT",
    "productId": 615034.0,
    "imageCount": 1.0,
    "score": 2.8585372,
    "setName": "Aetherdrift",
    "sellers": 1354.0,
    "foilOnly": false,
    "setUrlName": "Aetherdrift",
    "sellerListable": true,
    "productLineId": 1.0,
    "productStatusId": 1.0,
    "productLineName": "Magic: The Gathering",
    "maxFulfillableQuantity": 255.0,
    "normalOnly": false,
    "listings": 1878.0,
    "lowestPrice": 0.01,
    "medianPrice": 0.25,
    "formattedAttributes": {
      "Rarity": "C",
      "#": "17",
      "Card Type": "Artifact Creature — Robot Pilot",
      "P / T": "0 / 4",
      "Description": "This creature saddles Mounts and crews Vehicles using its toughness rather than its power.\r\n<br>\r\nWhenever this creature becomes tapped during your turn, untap it. This ability triggers only once each turn.",
      "Flavor": "<em>To the Guidelight Voyagers, a vehicle is just another hardware upgrade.</em>",
      "Artist": "Wonchun Choi"
    },
    "skus": [
      {
        "sku": 8532472,
        "condition": "Near Mint",
        "variant": "Normal",
        "language": "English"
      },
      {
        "sku": 8532473,
        "condition": "Lightly Played",
        "variant": "Normal",
        "language": "English"
      },
      {
        "sku": 8532474,
        "condition": "Moderately Played",
        "variant": "Normal",
        "language": "English"
      },
      {
        "sku": 8532475,
        "condition": "Heavily Played",
        "variant": "Normal",
        "language": "English"
      },
      {
        "sku": 8532476,
        "condition": "Damaged",
        "variant": "Normal",
        "language": "English"
      },
      {
        "sku": 8532477,
        "condition": "Near Mint",
        "variant": "Foil",
        "language": "English"
      },
      {
        "sku": 8532478,
        "condition": "Lightly Played",
        "variant": "Foil",
        "language": "English"
      },
      {
        "sku": 8532479,
        "condition": "Moderately Played",
        "variant": "Foil",
        "language": "English"
      },
      {
        "sku": 8532480,
        "condition": "Heavily Played",
        "variant": "Foil",
        "language": "English"
      },
      {
        "sku": 8532481,
        "condition": "Damaged",
        "variant": "Foil",
        "language": "English"
      },
      {
        "sku": 8532482,
        "condition": "Near Mint",
        "variant": "Normal",
        "language": "French"
      },
      {
        "sku": 8532483,
        "condition": "Lightly Played",
        "variant": "Normal",
        "language": "French"
      },
      {
        "sku": 8532484,
        "condition": "Moderately Played",
        "variant": "Normal",
        "language": "French"
      },
      {
        "sku": 8532485,
        "condition": "Heavily Played",
        "variant": "Normal",
        "language": "French"
      },
      {
        "sku": 8532486,
        "condition": "Damaged",
        "variant": "Normal",
        "language": "French"
      },
      {
        "sku": 8532487,
        "condition": "Near Mint",
        "variant": "Foil",
        "language": "French"
      },
      {
        "sku": 8532488,
        "condition": "Lightly Played",
        "variant": "Foil",
        "language": "French"
      },
      {
        "sku": 8532489,
        "condition": "Moderately Played",
        "variant": "Foil",
        "language": "French"
      },
      {
        "sku": 8532490,
        "condition": "Heavily Played",
        "variant": "Foil",
        "language": "French"
      },
      {
        "sku": 8532491,
        "condition": "Damaged",
        "variant": "Foil",
        "language": "French"
      },
      {
        "sku": 8532492,
        "condition": "Near Mint",
        "variant": "Normal",
        "language": "German"
      },
      {
        "sku": 8532493,
        "condition": "Lightly Played",
        "variant": "Normal",
        "language": "German"
      },
      {
        "sku": 8532494,
        "condition": "Moderately Played",
        "variant": "Normal",
        "language": "German"
      },
      {
        "sku": 8532495,
        "condition": "Heavily Played",
        "variant": "Normal",
        "language": "German"
      },
      {
        "sku": 8532496,
        "condition": "Damaged",
        "variant": "Normal",
        "language": "German"
      },
      {
        "sku": 8532497,
        "condition": "Near Mint",
        "variant": "Foil",
        "language": "German"
      },
      {
        "sku": 8532498,
        "condition": "Lightly Played",
        "variant": "Foil",
        "language": "German"
      },
      {
        "sku": 8532499,
        "condition": "Moderately Played",
        "variant": "Foil",
        "language": "German"
      },
      {
        "sku": 8532500,
        "condition": "Heavily Played",
        "variant": "Foil",
        "language": "German"
      },
      {
        "sku": 8532501,
        "condition": "Damaged",
        "variant": "Foil",
        "language": "German"
      },
      {
        "sku": 8532502,
        "condition": "Near Mint",
        "variant": "Normal",
        "language": "Italian"
      },
      {
        "sku": 8532503,
        "condition": "Lightly Played",
        "variant": "Normal",
        "language": "Italian"
      },
      {
        "sku": 8532504,
        "condition": "Moderately Played",
        "variant": "Normal",
        "language": "Italian"
      },
      {
        "sku": 8532505,
        "condition": "Heavily Played",
        "variant": "Normal",
        "language": "Italian"
      },
      {
        "sku": 8532506,
        "condition": "Damaged",
        "variant": "Normal",
        "language": "Italian"
      },
      {
        "sku": 8532507,
        "condition": "Near Mint",
        "variant": "Foil",
        "language": "Italian"
      },
      {
        "sku": 8532508,
        "condition": "Lightly Played",
        "variant": "Foil",
        "language": "Italian"
      },
      {
        "sku": 8532509,
        "condition": "Moderately Played",
        "variant": "Foil",
        "language": "Italian"
      },
      {
        "sku": 8532510,
        "condition": "Heavily Played",
        "variant": "Foil",
        "language": "Italian"
      },
      {
        "sku": 8532511,
        "condition": "Damaged",
        "variant": "Foil",
        "language": "Italian"
      },
      {
        "sku": 8532512,
        "condition": "Near Mint",
        "variant": "Normal",
        "language": "Japanese"
      },
      {
        "sku": 8532513,
        "condition": "Lightly Played",
        "variant": "Normal",
        "language": "Japanese"
      },
      {
        "sku": 8532514,
        "condition": "Moderately Played",
        "variant": "Normal",
        "language": "Japanese"
      },
      {
        "sku": 8532515,
        "condition": "Heavily Played",
        "variant": "Normal",
        "language": "Japanese"
      },
      {
        "sku": 8532516,
        "condition": "Damaged",
        "variant": "Normal",
        "language": "Japanese"
      },
      {
        "sku": 8532517,
        "condition": "Near Mint",
        "variant": "Foil",
        "language": "Japanese"
      },
      {
        "sku": 8532518,
        "condition": "Lightly Played",
        "variant": "Foil",
        "language": "Japanese"
      },
      {
        "sku": 8532519,
        "condition": "Moderately Played",
        "variant": "Foil",
        "language": "Japanese"
      },
      {
        "sku": 8532520,
        "condition": "Heavily Played",
        "variant": "Foil",
        "language": "Japanese"
      },
      {
        "sku": 8532521,
        "condition": "Damaged",
        "variant": "Foil",
        "language": "Japanese"
      },
      {
        "sku": 8532522,
        "condition": "Near Mint",
        "variant": "Normal",
        "language": "Spanish"
      },
      {
        "sku": 8532523,
        "condition": "Lightly Played",
        "variant": "Normal",
        "language": "Spanish"
      },
      {
        "sku": 8532524,
        "condition": "Moderately Played",
        "variant": "Normal",
        "language": "Spanish"
      },
      {
        "sku": 8532525,
        "condition": "Heavily Played",
        "variant": "Normal",
        "language": "Spanish"
      },
      {
        "sku": 8532526,
        "condition": "Damaged",
        "variant": "Normal",
        "language": "Spanish"
      },
      {
        "sku": 8532527,
        "condition": "Near Mint",
        "variant": "Foil",
        "language": "Spanish"
      },
      {
        "sku": 8532528,
        "condition": "Lightly Played",
        "variant": "Foil",
        "language": "Spanish"
      },
      {
        "sku": 8532529,
        "condition": "Moderately Played",
        "variant": "Foil",
        "language": "Spanish"
      },
      {
        "sku": 8532530,
        "condition": "Heavily Played",
        "variant": "Foil",
        "language": "Spanish"
      },
      {
        "sku": 8532531,
        "condition": "Damaged",
        "variant": "Foil",
        "language": "Spanish"
      }
    ]
  }
}
